buildington/__init__.py
buildington-1.6.dist-info/METADATA
buildington-1.6.dist-info/WHEEL
buildington-1.6.dist-info/top_level.txt
buildington-1.6.dist-info/RECORD
